netifaces-stubs/METADATA.toml
netifaces-stubs/__init__.pyi
netifaces-stubs/py.typed
types_netifaces-0.11.0.20241022.dist-info/METADATA
types_netifaces-0.11.0.20241022.dist-info/WHEEL
types_netifaces-0.11.0.20241022.dist-info/top_level.txt
types_netifaces-0.11.0.20241022.dist-info/RECORD
